tsoc_data_analysis/__init__.py
tsoc_data_analysis/excel_data_processor.py
tsoc_data_analysis/operating_point_extractor.py
tsoc_data_analysis/power_analysis_cli.py
tsoc_data_analysis/power_data_validator.py
tsoc_data_analysis/power_system_analytics.py
tsoc_data_analysis/power_system_visualizer.py
tsoc_data_analysis/system_configuration.py
tsoc_data_analysis-1.3.1.dist-info/licenses/LICENSE
tsoc_data_analysis-1.3.1.dist-info/licenses/NOTICE
tsoc_data_analysis-1.3.1.dist-info/METADATA
tsoc_data_analysis-1.3.1.dist-info/WHEEL
tsoc_data_analysis-1.3.1.dist-info/entry_points.txt
tsoc_data_analysis-1.3.1.dist-info/top_level.txt
tsoc_data_analysis-1.3.1.dist-info/RECORD
