Metadata-Version: 2.4
Name: tsoc-data-analysis
Version: 1.3.1
Summary: A comprehensive Python tool for analyzing TSOC power system operational data from Excel files
Author-email: "Sustainable Power Systems Lab (SPSL)" <info@sps-lab.org>
Maintainer-email: "Sustainable Power Systems Lab (SPSL)" <info@sps-lab.org>
License: Apache-2.0
Project-URL: Homepage, https://sps-lab.org
Project-URL: Repository, https://github.com/sps-lab/tsoc-data-analysis
Project-URL: Documentation, https://tsoc-data-analysis.readthedocs.io/
Project-URL: Bug Tracker, https://github.com/sps-lab/tsoc-data-analysis/issues
Keywords: power systems,data analysis,excel,clustering,operating points
Classifier: Development Status :: 4 - Beta
Classifier: Intended Audience :: Science/Research
Classifier: License :: OSI Approved :: Apache Software License
Classifier: Operating System :: OS Independent
Classifier: Programming Language :: Python :: 3
Classifier: Programming Language :: Python :: 3.8
Classifier: Programming Language :: Python :: 3.9
Classifier: Programming Language :: Python :: 3.10
Classifier: Programming Language :: Python :: 3.11
Classifier: Topic :: Scientific/Engineering :: Information Analysis
Classifier: Topic :: Utilities
Requires-Python: >=3.8
License-File: LICENSE
License-File: NOTICE
Requires-Dist: pandas>=1.5.0
Requires-Dist: numpy>=1.23.0
Requires-Dist: matplotlib>=3.7.0
Requires-Dist: seaborn>=0.12.2
Requires-Dist: openpyxl>=3.1.2
Requires-Dist: xlsxwriter>=3.0.0
Requires-Dist: xlrd>=2.0.0
Requires-Dist: scikit-learn>=1.2.0
Requires-Dist: scipy>=1.10.0
Requires-Dist: psutil>=5.8.0
Requires-Dist: joblib>=1.1.0
Requires-Dist: jupyter>=1.0.0
Requires-Dist: ipython>=8.0.0
Requires-Dist: ipykernel>=6.0.0
Requires-Dist: tqdm>=4.64.0
Requires-Dist: pydantic>=1.10.0
Provides-Extra: dev
Requires-Dist: pytest>=6.0.0; extra == "dev"
Requires-Dist: pytest-cov>=2.10.0; extra == "dev"
Requires-Dist: black>=21.0.0; extra == "dev"
Requires-Dist: flake8>=3.8.0; extra == "dev"
Requires-Dist: mypy>=0.800; extra == "dev"
Provides-Extra: docs
Requires-Dist: sphinx>=7.0.0; extra == "docs"
Requires-Dist: sphinx-rtd-theme>=2.0.0; extra == "docs"
Requires-Dist: sphinx-autodoc-typehints>=1.25.0; extra == "docs"
Requires-Dist: sphinx-latex-parser>=1.0.0; extra == "docs"
Dynamic: license-file
